LICENSE
MANIFEST.in
README.rst
setup.cfg
setup.py
python_voc_parser/__init__.py
python_voc_parser/helpers.py
python_voc_parser/voc_annotations_parser.py
python_voc_parser.egg-info/PKG-INFO
python_voc_parser.egg-info/SOURCES.txt
python_voc_parser.egg-info/dependency_links.txt
python_voc_parser.egg-info/not-zip-safe
python_voc_parser.egg-info/requires.txt
python_voc_parser.egg-info/top_level.txt