Metadata-Version: 1.1
Name: python-voc-parser
Version: 1.0.0
Summary: Python pascal voc dataset parset
Home-page: https://github.com/gabrielrezzonico/python_voc_parser
Author: Gabriel Rezzonico
Author-email: gabrielrezzonico@gmail.com
License: MIT
Download-URL: https://github.com/gabrielrezzonico/python_voc_parser/tarball/1.0.0
Platform: UNKNOWN
Classifier: Development Status :: 3 - Alpha
Classifier: License :: OSI Approved :: MIT License
Classifier: Programming Language :: Python :: 3.5
Classifier: Intended Audience :: Developers
Classifier: Intended Audience :: Science/Research
Classifier: Topic :: Utilities
Classifier: Topic :: Software Development :: Libraries
